parts/__init__.py
parts/ansi_stream.py
parts/color.py
parts/common.py
parts/config.py
parts/console.py
parts/datacache.py
parts/dependent_ref.py
parts/dependson.py
parts/engine.py
parts/errors.py
parts/exportitem.py
parts/filters.py
parts/functors.py
parts/glb.py
parts/installs.py
parts/load_module.py
parts/logger.py
parts/main.py
parts/mappers.py
parts/metatag.py
parts/node_helpers.py
parts/packaging.py
parts/part_logger.py
parts/part_manager.py
parts/part_ref.py
parts/parts.py
parts/parts_version.py
parts/pattern.py
parts/picklehelpers.py
parts/platform_info.py
parts/poptions.py
parts/process_tools.py
parts/reporter.py
parts/requirement.py
parts/sdk.py
parts/settings.py
parts/target_type.py
parts/tool_mapping.py
parts/version.py
parts/version_info.py
parts/Variables/BoolVariable.py
parts/Variables/EnumVariable.py
parts/Variables/IntVariable.py
parts/Variables/ListVariable.py
parts/Variables/PackageVariable.py
parts/Variables/PathVariable.py
parts/Variables/__init__.py
parts/Variables/variable.py
parts/Variables/variables.py
parts/api/__init__.py
parts/api/output.py
parts/api/platforms.py
parts/api/register.py
parts/api/requirement.py
parts/api/vcs.py
parts/configurations/__init__.py
parts/configurations/debug/__init__.py
parts/configurations/debug/clang_darwin-any_darwin-any.py
parts/configurations/debug/g++.py
parts/configurations/debug/g++_any-any_android-arm.py
parts/configurations/debug/g++_any-any_android-x86.py
parts/configurations/debug/g++_any-any_android-x86_64.py
parts/configurations/debug/gcc.py
parts/configurations/debug/gcc_any-any_android-arm.py
parts/configurations/debug/gcc_any-any_android-x86.py
parts/configurations/debug/gcc_any-any_android-x86_64.py
parts/configurations/debug/intelc_posix-any.py
parts/configurations/debug/intelc_posix-any_posix-k1om.py
parts/configurations/debug/intelc_win32-any.py
parts/configurations/debug/msvc_win32-any.py
parts/configurations/debug/wdk_win32-any_win32-x86.py
scons_parts-0.18.5.dist-info/METADATA
scons_parts-0.18.5.dist-info/WHEEL
scons_parts-0.18.5.dist-info/entry_points.txt
scons_parts-0.18.5.dist-info/license.txt
scons_parts-0.18.5.dist-info/top_level.txt
scons_parts-0.18.5.dist-info/RECORD
