Metadata-Version: 2.1
Name: scons-parts
Version: 0.18.5
Summary: Extension module to SCons build system
Author-email: Jason Kenny <dragon512@live.com>
License: Copyright (c) 2008-2023 Jason Kenny and contributors
Project-URL: Source Code, https://bitbucket.org/sconsparts/parts
Project-URL: Documentation, https://sconsparts.bitbucket.io/index.html
Keywords: build,SCons,extension
Classifier: Development Status :: 5 - Production/Stable
Classifier: Environment :: Console
Classifier: Intended Audience :: Developers
Classifier: License :: OSI Approved :: MIT License
Classifier: Operating System :: OS Independent
Classifier: Programming Language :: Python :: 3
Classifier: Programming Language :: Python :: 3.8
Classifier: Programming Language :: Python :: 3.9
Classifier: Programming Language :: Python :: 3.10
Classifier: Programming Language :: Python :: 3.11
Classifier: Programming Language :: Python :: 3.12
Classifier: Programming Language :: Python :: 3.13
Classifier: Topic :: Terminals
Classifier: Programming Language :: Python :: 3 :: Only
Requires-Python: >=3.6
License-File: license.txt
Requires-Dist: scons
Provides-Extra: dev
Requires-Dist: nox; extra == "dev"
Requires-Dist: autest; extra == "dev"
Requires-Dist: pytest; extra == "dev"
Requires-Dist: pylama; extra == "dev"
Requires-Dist: mypy; extra == "dev"
Requires-Dist: autopep8; extra == "dev"
Requires-Dist: sphinx; extra == "dev"
Requires-Dist: myst-parser; extra == "dev"
Requires-Dist: karma-sphinx-theme; extra == "dev"
